{
  "name": "Betty Chavez",
  "age": 55,
  "address": {
    "street": "Kica Heights",
    "city": "Hipumi",
    "state": "IL",
    "zip": "68756"
  },
  "contact": {
    "phone": "(337) 329-1716",
    "servicePhone": "800624469"
  },
  "birthday": "1974-12-11T03:32:21.015Z",
  "ip": "182.93.18.168",
  "foo": "bar",
  "profile": {
    "about": "Mumoate fac ozu sow sehuguf duhzoc usiibojis feviv fafco dozaah ed bebgip fed seebo jojwi zinda sa po. Acewaci tumizi durbamdaz warip aruloh zapeg vorda ric ese ov mahe ga. Wuzhip gutle raha imsoz pa ni siirweg nig bedmoke ze ribdut nehooh ozoti.",
    "bio": "Giktug der mioppop itoji na ajzuw kagoli so iso tel lomtof bodefi hucnojfes pu loppiwoh okoafuen vozsuj uwubi. Awsezal joh kahsito bilvados vu kum itbi ad menu enifiwme sozvel go jemo wikbi sa pehmiti hehriw. Lucom po gegfieb el mikveb tuasi cusniwon wueri zojotodo raja radun fase et hihuw lekkucu afolo. Una fawcarmul omil gadwaeb ki mivo cijwutiz javjab dekijgus apohuki osu panihbop kuwu wicujud cisoskes vulsime."
  },
  "apiKey": "6542f4781374d5c09bb2c33356d7e569cb190d4c54ca31184d6f29243e8d3af6",
  "currency": {
    "code": "SDG",
    "name": "Sudan Pound"
  }
}